autotracer/__init__.py
autotracer/auto_tracer.py
autotracer/mock.py
autotracer-0.0.2.data/scripts/auto_tracer.py
autotracer-0.0.2.dist-info/LICENSE
autotracer-0.0.2.dist-info/METADATA
autotracer-0.0.2.dist-info/WHEEL
autotracer-0.0.2.dist-info/top_level.txt
autotracer-0.0.2.dist-info/RECORD
