Metadata-Version: 2.1
Name: autotracer
Version: 0.0.2
Summary: Runs a code tracer in simple Python scripts for educational purposes
Home-page: https://github.com/toshikurauchi/autotracer
Author: Andrew Kurauchi
Author-email: andrewtnk@insper.edu.br
License: MIT
Platform: UNKNOWN
Classifier: License :: OSI Approved :: MIT License
Classifier: Programming Language :: Python :: 3
Classifier: Programming Language :: Python :: 3.7
